LICENSE.md
README.md
setup.cfg
setup.py
src/testit_api_client/__init__.py
src/testit_api_client/api_client.py
src/testit_api_client/configuration.py
src/testit_api_client/exceptions.py
src/testit_api_client/model_utils.py
src/testit_api_client/rest.py
src/testit_api_client.egg-info/PKG-INFO
src/testit_api_client.egg-info/SOURCES.txt
src/testit_api_client.egg-info/dependency_links.txt
src/testit_api_client.egg-info/requires.txt
src/testit_api_client.egg-info/top_level.txt
src/testit_api_client/api/__init__.py
src/testit_api_client/api/attachments_api.py
src/testit_api_client/api/auto_tests_api.py
src/testit_api_client/api/background_jobs_api.py
src/testit_api_client/api/configurations_api.py
src/testit_api_client/api/custom_attribute_templates_api.py
src/testit_api_client/api/custom_attributes_api.py
src/testit_api_client/api/external_issues_api.py
src/testit_api_client/api/notifications_api.py
src/testit_api_client/api/parameters_api.py
src/testit_api_client/api/project_attribute_templates_api.py
src/testit_api_client/api/project_attributes_api.py
src/testit_api_client/api/project_configurations_api.py
src/testit_api_client/api/project_sections_api.py
src/testit_api_client/api/project_settings_api.py
src/testit_api_client/api/project_test_plan_attributes_api.py
src/testit_api_client/api/project_test_plan_test_points_api.py
src/testit_api_client/api/project_test_plans_api.py
src/testit_api_client/api/project_work_items_api.py
src/testit_api_client/api/projects_api.py
src/testit_api_client/api/search_api.py
src/testit_api_client/api/sections_api.py
src/testit_api_client/api/tags_api.py
src/testit_api_client/api/test_plans_api.py
src/testit_api_client/api/test_points_api.py
src/testit_api_client/api/test_results_api.py
src/testit_api_client/api/test_runs_api.py
src/testit_api_client/api/test_suites_api.py
src/testit_api_client/api/users_api.py
src/testit_api_client/api/webhooks_api.py
src/testit_api_client/api/webhooks_logs_api.py
src/testit_api_client/api/work_items_api.py
src/testit_api_client/api/work_items_comments_api.py
src/testit_api_client/apis/__init__.py
src/testit_api_client/model/__init__.py
src/testit_api_client/model/action_update.py
