Metadata-Version: 2.4
Name: testit-api-client
Version: 7.4.0
Summary: API-client for Test IT
Home-page: https://pypi.org/project/testit-api-client/
Author: Integration team
Author-email: integrations@testit.software
Requires-Python: >=3.7
License-File: LICENSE.md
Requires-Dist: urllib3<3.0.0,>=1.25.3
Requires-Dist: python-dateutil
Dynamic: author
Dynamic: author-email
Dynamic: description
Dynamic: description-content-type
Dynamic: home-page
Dynamic: license-file
Dynamic: requires-dist
Dynamic: requires-python
Dynamic: summary
